xcp/__init__.py
xcp/py.typed
universal_calibration_protocol-0.3.0.dist-info/METADATA
universal_calibration_protocol-0.3.0.dist-info/WHEEL
universal_calibration_protocol-0.3.0.dist-info/RECORD
