Metadata-Version: 2.4
Name: universal-calibration-protocol
Version: 0.3.0
Summary: Pure python xcp protocol implementation
Project-URL: Repository, https://github.com/Nicoretti/xcp
Project-URL: Homepage, https://nicoretti.github.io/xcp/
Project-URL: Documentation, https://nicoretti.github.io/xcp/
Project-URL: Source, https://github.com/Nicoretti/xcp
Project-URL: Issues, https://github.com/Nicoretti/xcp/issues
Author-email: Nicola Coretti <nico.coretti@gmail.com>
Maintainer-email: Nicola Coretti <nico.coretti@gmail.com>
License-Expression: MIT
Keywords: automotive,autosar,ecu,xcp
Classifier: Development Status :: 3 - Alpha
Classifier: License :: OSI Approved :: MIT License
Classifier: Programming Language :: Python :: 3.11
Classifier: Programming Language :: Python :: 3.12
Classifier: Programming Language :: Python :: 3.13
Classifier: Programming Language :: Python :: 3.14
Requires-Python: >=3.11
